spark_data_modeling_tools/__init__.py
spark_data_modeling_tools/functions/__init__.py
spark_data_modeling_tools/functions/generator.py
spark_data_modeling_tools-0.1.7.dist-info/LICENSE
spark_data_modeling_tools-0.1.7.dist-info/METADATA
spark_data_modeling_tools-0.1.7.dist-info/WHEEL
spark_data_modeling_tools-0.1.7.dist-info/top_level.txt
spark_data_modeling_tools-0.1.7.dist-info/RECORD
