Metadata-Version: 2.1
Name: spark-data-modeling-tools
Version: 0.1.7
Summary: spark_data_modeling_tools
Home-page: https://github.com/jonaqp/spark_data_modeling_tools/
Author: Jonathan Quiza
Author-email: jony327@gmail.com
License: UNKNOWN
Download-URL: https://github.com/jonaqp/spark_data_modeling_tools/archive/main.zip
Keywords: spark,dataframe,modeling
Platform: UNKNOWN
Classifier: Development Status :: 5 - Production/Stable
Classifier: Intended Audience :: Developers
Classifier: Intended Audience :: Science/Research
Classifier: Topic :: Scientific/Engineering :: Artificial Intelligence
Classifier: License :: OSI Approved :: Apache Software License
Classifier: Programming Language :: Python :: 3.9
License-File: LICENSE
Requires-Dist: spark-dataframe-tools (>=0.5.5)
Requires-Dist: openpyxl (==3.1.2)
